scotpy/benchmark.py
scotpy/plot_bench_res.py
scotpy/scotpy.py
scotpy-1.0.0.dist-info/AUTHORS
scotpy-1.0.0.dist-info/LICENSE
scotpy-1.0.0.dist-info/METADATA
scotpy-1.0.0.dist-info/WHEEL
scotpy-1.0.0.dist-info/top_level.txt
scotpy-1.0.0.dist-info/RECORD
