Metadata-Version: 2.1
Name: scotpy
Version: 1.0.0
Summary: SCOT solver python api
Author-email: Alireza Olama <alireza.lm69@gmail.com>
License: Eclipse Public License - v 2.0
Project-URL: Homepage, https://github.com/alirezalm/scotpy
Requires-Python: >=3.7
License-File: LICENSE
License-File: AUTHORS
Requires-Dist: numpy
Requires-Dist: scikit-learn
Requires-Dist: scipy
Requires-Dist: matplotlib
Requires-Dist: pyomo
